openinference/instrumentation/instructor/__init__.py
openinference/instrumentation/instructor/_wrappers.py
openinference/instrumentation/instructor/version.py
openinference_instrumentation_instructor-0.1.12.dist-info/METADATA
openinference_instrumentation_instructor-0.1.12.dist-info/WHEEL
openinference_instrumentation_instructor-0.1.12.dist-info/entry_points.txt
openinference_instrumentation_instructor-0.1.12.dist-info/licenses/LICENSE
openinference_instrumentation_instructor-0.1.12.dist-info/RECORD
