Metadata-Version: 2.4
Name: openinference-instrumentation-instructor
Version: 0.1.12
Summary: OpenInference Instructor Instrumentation
Project-URL: Homepage, https://github.com/Arize-ai/openinference/tree/main/python/instrumentation/openinference-instrumentation-instructor
Author-email: OpenInference Authors <oss@arize.com>
License-Expression: Apache-2.0
License-File: LICENSE
Classifier: Development Status :: 5 - Production/Stable
Classifier: Intended Audience :: Developers
Classifier: License :: OSI Approved :: Apache Software License
Classifier: Programming Language :: Python
Classifier: Programming Language :: Python :: 3
Classifier: Programming Language :: Python :: 3.9
Classifier: Programming Language :: Python :: 3.10
Classifier: Programming Language :: Python :: 3.11
Classifier: Programming Language :: Python :: 3.12
Requires-Python: <3.14,>=3.9
Requires-Dist: openinference-instrumentation>=0.1.27
Requires-Dist: openinference-semantic-conventions>=0.1.17
Requires-Dist: opentelemetry-api
Requires-Dist: opentelemetry-instrumentation
Requires-Dist: opentelemetry-semantic-conventions
Requires-Dist: typing-extensions
Requires-Dist: wrapt
Provides-Extra: instruments
Requires-Dist: instructor>=1.3.7; extra == 'instruments'
Provides-Extra: test
Requires-Dist: instructor==1.3.7; extra == 'test'
Requires-Dist: opentelemetry-sdk; extra == 'test'
Requires-Dist: responses; extra == 'test'
Requires-Dist: vcrpy; extra == 'test'
